vsort/__init__.py
vsort-1.0.2.dist-info/LICENSE
vsort-1.0.2.dist-info/METADATA
vsort-1.0.2.dist-info/WHEEL
vsort-1.0.2.dist-info/top_level.txt
vsort-1.0.2.dist-info/RECORD
